Metadata-Version: 2.1
Name: application-client
Version: 0.0.1
Summary: Application Client
Home-page: UNKNOWN
Author: Kamenev Vladimir
Author-email: kvv23@tut.by
License: UNKNOWN
Platform: UNKNOWN
Requires-Dist: PyQt5
Requires-Dist: pycryptodome
Requires-Dist: pycryptodomex
Requires-Dist: sqlalchemy
